Polar_codes_BEC/__init__.py
Polar_codes_BEC/bec_polar_lib.py
Polar_codes_BEC-1.2.3.dist-info/METADATA
Polar_codes_BEC-1.2.3.dist-info/WHEEL
Polar_codes_BEC-1.2.3.dist-info/top_level.txt
Polar_codes_BEC-1.2.3.dist-info/RECORD
