Metadata-Version: 2.1
Name: Polar-codes-BEC
Version: 1.2.3
Summary: Polar_codes_BEC
Home-page: https://pypi.org/project/Polar-codes-BEC/
Author: Issame EL KAIME and AIT MADI Abdessalam
Author-email: issame.elkaime@uit.ac.ma
License: MIT
Platform: UNKNOWN
Classifier: Operating System :: OS Independent
Classifier: License :: OSI Approved :: MIT License
Classifier: Programming Language :: Python
Classifier: Programming Language :: Python :: 3
Classifier: Programming Language :: Python :: 3.6
Classifier: Programming Language :: Python :: 3.7
Classifier: Programming Language :: Python :: 3.8
Classifier: Programming Language :: Python :: 3.9
Classifier: Operating System :: OS Independent
Requires-Dist: numpy
